{
  "$schema": "https://developer.microsoft.com/json-schemas/fabric/item/report/definition/visualContainer/2.4.0/schema.json",
  "name": "1d98690d9660a94b33bb",
  "position": {
    "x": 944.08549556944013,
    "y": 153.31215671465398,
    "z": 7,
    "height": 200.34372435049164,
    "width": 300.51558652573749
  },
  "visual": {
    "visualType": "card",
    "query": {
      "queryState": {
        "Values": {
          "projections": [
            {
              "field": {
                "Measure": {
                  "Expression": {
                    "SourceRef": {
                      "Entity": "fact_sales"
                    }
                  },
                  "Property": "Orders YoY"
                }
              },
              "queryRef": "fact_sales.Orders YoY %",
              "nativeQueryRef": "Orders YoY %",
              "format": "0%;-0%;0%"
            }
          ]
        }
      },
      "sortDefinition": {
        "sort": [
          {
            "field": {
              "Measure": {
                "Expression": {
                  "SourceRef": {
                    "Entity": "fact_sales"
                  }
                },
                "Property": "Orders YoY"
              }
            },
            "direction": "Descending"
          }
        ],
        "isDefaultSort": true
      }
    },
    "objects": {
      "labels": [
        {
          "properties": {
            "fontFamily": {
              "expr": {
                "Literal": {
                  "Value": "'''Segoe UI'', wf_segoe-ui_normal, helvetica, arial, sans-serif'"
                }
              }
            },
            "fontSize": {
              "expr": {
                "Literal": {
                  "Value": "48D"
                }
              }
            },
            "color": {
              "solid": {
                "color": {
                  "expr": {
                    "ThemeDataColor": {
                      "ColorId": 1,
                      "Percent": 0.4
                    }
                  }
                }
              }
            }
          }
        }
      ],
      "categoryLabels": [
        {
          "properties": {
            "color": {
              "solid": {
                "color": {
                  "expr": {
                    "ThemeDataColor": {
                      "ColorId": 1,
                      "Percent": 0.4
                    }
                  }
                }
              }
            },
            "fontSize": {
              "expr": {
                "Literal": {
                  "Value": "24D"
                }
              }
            }
          }
        }
      ]
    },
    "visualContainerObjects": {
      "background": [
        {
          "properties": {
            "color": {
              "solid": {
                "color": {
                  "expr": {
                    "Literal": {
                      "Value": "'#CBF8F3'"
                    }
                  }
                }
              }
            }
          }
        }
      ]
    },
    "drillFilterOtherVisuals": true
  },
  "filterConfig": {
    "filters": [
      {
        "name": "d4faca178eaca1c1d68a",
        "field": {
          "Measure": {
            "Expression": {
              "SourceRef": {
                "Entity": "fact_sales"
              }
            },
            "Property": "Orders YoY"
          }
        },
        "type": "Advanced"
      }
    ]
  }
}